reapit_cdk/replicated_key/__init__.py
reapit_cdk/replicated_key/py.typed
reapit_cdk/replicated_key/_jsii/__init__.py
reapit_cdk/replicated_key/_jsii/replicated-key@0.1.2.jsii.tgz
reapit_cdk.replicated_key-0.1.2.dist-info/LICENSE
reapit_cdk.replicated_key-0.1.2.dist-info/METADATA
reapit_cdk.replicated_key-0.1.2.dist-info/WHEEL
reapit_cdk.replicated_key-0.1.2.dist-info/top_level.txt
reapit_cdk.replicated_key-0.1.2.dist-info/RECORD
